{"S.N.": {"0": 1.0, "1": 2.0, "2": 3.0, "3": 4.0, "4": 5.0, "5": 6.0, "6": 7.0, "7": 8.0, "8": 9.0, "9": 10.0}, "Candidate": {"0": "ASHWINI KUMAR SARANGI", "1": "ASHISH SATPATHY", "2": "JAYASHANKAR SINHA", "3": "DEBESH ACHARYA", "4": "NIPON KUMAR DASH", "5": "MUKTA NAG", "6": "NANDA NANDAN MAHANANDA", "7": "PANDABA KARNA", "8": "BHAKTA BINOD BABA", "9": "NOTA"}, "Party": {"0": "Bharatiya Janata Party", "1": "Aam Aadmi Party", "2": "Bahujan Samaj Party", "3": "Biju Janata Dal", "4": "Indian National Congress", "5": "Rashtriya Manav Party", "6": "Independent", "7": "Independent", "8": "Independent", "9": "None of the Above"}, "EVM Votes": {"0": 77049, "1": 692, "2": 1197, "3": 72406, "4": 10174, "5": 381, "6": 2059, "7": 471, "8": 753, "9": 1162}, "Postal Votes": {"0": 717, "1": 10, "2": 5, "3": 588, "4": 98, "5": 3, "6": 21, "7": 5, "8": 4, "9": 25}, "Total Votes": {"0": 77766, "1": 702, "2": 1202, "3": 72994, "4": 10272, "5": 384, "6": 2080, "7": 476, "8": 757, "9": 1187}, "% of Votes": {"0": 46.34, "1": 0.42, "2": 0.72, "3": 43.5, "4": 6.12, "5": 0.23, "6": 1.24, "7": 0.28, "8": 0.45, "9": 0.71}, "Total": {"Candidate": "Total", "EVM Votes": 166344, "Postal Votes": 1476, "Total Votes": 167820}}