{"S.N.": {"0": 1.0, "1": 2.0, "2": 3.0, "3": 4.0, "4": 5.0, "5": 6.0, "6": 7.0}, "Candidate": {"0": "TULESWAR NAIK", "1": "DIBYA SHANKAR MISHRA", "2": "MANOJ KUMAR MEHER", "3": "RABI HARIJAN", "4": "PARAMESWAR KAND", "5": "SUDHANIDHI NAIK", "6": "NOTA"}, "Party": {"0": "Indian National Congress", "1": "Biju Janata Dal", "2": "Bharatiya Janata Party", "3": "Odisha Janata Party", "4": "Independent", "5": "Independent", "6": "None of the Above"}, "EVM Votes": {"0": 39052, "1": 76483, "2": 75104, "3": 1604, "4": 1467, "5": 1307, "6": 2725}, "Postal Votes": {"0": 440, "1": 554, "2": 595, "3": 7, "4": 4, "5": 2, "6": 10}, "Total Votes": {"0": 39492, "1": 77037, "2": 75699, "3": 1611, "4": 1471, "5": 1309, "6": 2735}, "% of Votes": {"0": 19.81, "1": 38.64, "2": 37.97, "3": 0.81, "4": 0.74, "5": 0.66, "6": 1.37}, "Total": {"Candidate": "Total", "EVM Votes": 197742, "Postal Votes": 1612, "Total Votes": 199354}}