{"S.N.": {"0": 1.0, "1": 2.0, "2": 3.0, "3": 4.0, "4": 5.0, "5": 6.0, "6": 7.0, "7": 8.0, "8": 9.0, "9": 10.0, "10": 11.0, "11": 12.0, "12": 13.0, "13": 14.0, "14": 15.0, "15": 16.0, "16": 17.0, "17": 18.0, "18": 19.0, "19": 20.0, "20": 21.0}, "Candidate": {"0": "BHAUSAHEB RAJARAM WAKCHAURE", "1": "LOKHANDE SADASHIV KISAN", "2": "UTKARSHA PREMANAND RUPWATE", "3": "BHAUSAHEB RAMNATH WAKCHAURE", "4": "RAMCHANDRA NAMDEV JADHAV", "5": "RAVINDRA KALLAYYA SWAMY", "6": "ABHIJEET ASHOKRAO POTE", "7": "BHARAT SAMBHAJI BHOSLE", "8": "SATISH BHIVA PAWAR", "9": "GANGADHAR RAJARAM KADAM", "10": "BAGUL GORAKSHA TANHAJI", "11": "PRASHANT VASANT NIKAM", "12": "ADV NITIN DADAHARI POL", "13": "RAJENDRA RATNAKAR WAGHMARE", "14": "ADV SIDHARTH DEEPAK BODHAK", "15": "CHANDRAKANT SAMBHAJI DONDE", "16": "ASHOK RAMCHANDRA ALHAT", "17": "KHAJEKAR VIJAYRAO GOVINDRAO", "18": "KHARAT NACHIKET RAGHUNATH", "19": "SANJAY POPAT BHALERAO", "20": "NOTA"}, "Party": {"0": "Shiv Sena (Uddhav Balasaheb Thackrey)", "1": "Shiv Sena", "2": "Vanchit Bahujan Aaghadi", "3": "Independent", "4": "Bahujan Samaj Party", "5": "Independent", "6": "Independent", "7": "Samata Party", "8": "Independent", "9": "Independent", "10": "Independent", "11": "Independent", "12": "Bahujan Bharat Party", "13": "Rashtriya Jankranti Party", "14": "Independent", "15": "Independent", "16": "Independent", "17": "Independent", "18": "Independent", "19": "Independent", "20": "None of the Above"}, "EVM Votes": {"0": 475637, "1": 425498, "2": 90748, "3": 13973, "4": 7000, "5": 5536, "6": 4761, "7": 3395, "8": 2765, "9": 2743, "10": 2658, "11": 2542, "12": 2517, "13": 2500, "14": 2202, "15": 2074, "16": 1794, "17": 1555, "18": 1146, "19": 958, "20": 5326}, "Postal Votes": {"0": 1263, "1": 873, "2": 181, "3": 33, "4": 40, "5": 1, "6": 15, "7": 8, "8": 6, "9": 14, "10": 2, "11": 3, "12": 15, "13": 5, "14": 2, "15": 6, "16": 4, "17": 2, "18": 4, "19": 5, "20": 54}, "Total Votes": {"0": 476900, "1": 426371, "2": 90929, "3": 14006, "4": 7040, "5": 5537, "6": 4776, "7": 3403, "8": 2771, "9": 2757, "10": 2660, "11": 2545, "12": 2532, "13": 2505, "14": 2204, "15": 2080, "16": 1798, "17": 1557, "18": 1150, "19": 963, "20": 5380}, "% of Votes": {"0": 45.0, "1": 40.23, "2": 8.58, "3": 1.32, "4": 0.66, "5": 0.52, "6": 0.45, "7": 0.32, "8": 0.26, "9": 0.26, "10": 0.25, "11": 0.24, "12": 0.24, "13": 0.24, "14": 0.21, "15": 0.2, "16": 0.17, "17": 0.15, "18": 0.11, "19": 0.09, "20": 0.51}}