{"S.N.": {"0": 1.0, "1": 2.0, "2": 3.0, "3": 4.0, "4": 5.0, "5": 6.0, "6": 7.0, "7": 8.0, "8": 9.0, "9": 10.0}, "Candidate": {"0": "KRITI DEVI DEBBARMAN", "1": "RAJENDRA REANG", "2": "ARCHANA URANG", "3": "DARSHAN KUMAR REANG", "4": "SANTOJOY TRIPURA", "5": "SHIB CHANDRA DEBBARMA", "6": "SATRUGHNA JAMATIA", "7": "KRISHNA MOHAN JAMATIA", "8": "KALPA MOHAN TRIPURA", "9": "NOTA"}, "Party": {"0": "Bharatiya Janata Party", "1": "Communist Party of India (Marxist)", "2": "Independent", "3": "Independent", "4": "Independent", "5": "Independent", "6": "Independent", "7": "Independent", "8": "Independent", "9": "None of the Above"}, "EVM Votes": {"0": 768129, "1": 287772, "2": 10814, "3": 9200, "4": 6825, "5": 6685, "6": 5939, "7": 4166, "8": 3958, "9": 18176}, "Postal Votes": {"0": 9318, "1": 2856, "2": 108, "3": 69, "4": 37, "5": 34, "6": 28, "7": 51, "8": 53, "9": 127}, "Total Votes": {"0": 777447, "1": 290628, "2": 10922, "3": 9269, "4": 6862, "5": 6719, "6": 5967, "7": 4217, "8": 4011, "9": 18303}, "% of Votes": {"0": 68.54, "1": 25.62, "2": 0.96, "3": 0.82, "4": 0.6, "5": 0.59, "6": 0.53, "7": 0.37, "8": 0.35, "9": 1.61}}