{"S.N.": {"0": 1.0, "1": 2.0, "2": 3.0, "3": 4.0, "4": 5.0, "5": 6.0, "6": 7.0, "7": 8.0, "8": 9.0, "9": 10.0, "10": 11.0, "11": 12.0, "12": 13.0, "13": 14.0}, "Candidate": {"0": "JAGADISH SHETTAR", "1": "MRINAL R HEBBALKAR", "2": "MAHADEV PATIL", "3": "BASAPPA GURUSIDDAPPA KUMBAR", "4": "ASHOK APPAYA APPUGOL", "5": "RAVI SHIVAPPA PADASALAGI", "6": "VIJAY S METHRANI", "7": "PRAJAAKEEYA MALLAPPA CHOGALA (PREM)", "8": "LAXMAN JADAGANNAVAR", "9": "NITIN ASHOK MHADAGUT", "10": "PUNDALIK ITNAL", "11": "ASHOK P HANAJI", "12": "ASHPAKAHMAD USTAD", "13": "NOTA"}, "Party": {"0": "Bharatiya Janata Party", "1": "Indian National Congress", "2": "Independent", "3": "Karnataka Rashtra Samithi", "4": "Bahujan Samaj Party", "5": "Independent", "6": "Independent", "7": "Uttama Prajaakeeya Party", "8": "Socialist Unity Centre Of India (COMMUNIST)", "9": "Independent", "10": "Independent", "11": "Independent", "12": "Independent", "13": "None of the Above"}, "EVM Votes": {"0": 756471, "1": 580897, "2": 9425, "3": 5406, "4": 4350, "5": 3911, "6": 2804, "7": 1413, "8": 1287, "9": 1286, "10": 1062, "11": 668, "12": 622, "13": 5683}, "Postal Votes": {"0": 5558, "1": 2695, "2": 78, "3": 35, "4": 57, "5": 15, "6": 4, "7": 20, "8": 15, "9": 24, "10": 37, "11": 11, "12": 12, "13": 43}, "Total Votes": {"0": 762029, "1": 583592, "2": 9503, "3": 5441, "4": 4407, "5": 3926, "6": 2808, "7": 1433, "8": 1302, "9": 1310, "10": 1099, "11": 679, "12": 634, "13": 5726}, "% of Votes": {"0": 55.06, "1": 42.17, "2": 0.69, "3": 0.39, "4": 0.32, "5": 0.28, "6": 0.2, "7": 0.1, "8": 0.09, "9": 0.09, "10": 0.08, "11": 0.05, "12": 0.05, "13": 0.41}}